{
 "status": "ok", 
 "result": {
  "p7202138": {
   "ownerKey": "s12495795", 
   "name": "open music labs", 
   "icon": "http://rdio0-a.akamaihd.net/_is/?aid=1464835-1&w=200&h=200", 
   "shortUrl": "http://rd.io/x/QeHp7DMytxs/", 
   "baseIcon": "album/3/0/a/0000000000165a03/1/square-200.jpg", 
   "ownerIcon": "user/3/b/b/0000000000beabb3/2/square-100.jpg", 
   "length": 1, 
   "lastUpdated": 1384818095.0, 
   "url": "/people/walkaway/playlists/7202138/open_music_labs/", 
   "tracks": [
    {
     "radioKey": "sr16421931", 
     "baseIcon": "album/3/0/a/0000000000165a03/1/square-200.jpg", 
     "canDownloadAlbumOnly": false, 
     "radio": {
      "type": "sr", 
      "key": "sr16421931"
     }, 
     "artistUrl": "/artist/Cubik__Origami/", 
     "duration": 234, 
     "dynamicIcon": "http://rdiodynimages1-a.akamaihd.net/?l=a1464835-1", 
     "album": "Slept In On Doomsday", 
     "isClean": false, 
     "albumUrl": "/artist/Cubik__Origami/album/Slept_In_On_Doomsday/", 
     "shortUrl": "http://rd.io/x/QeHp7Delxmo/", 
     "albumArtist": "Cubik & Origami", 
     "canStream": true, 
     "embedUrl": "https://rd.io/e/QeHp7Delxmo/", 
     "type": "t", 
     "gridIcon": "http://rdiodynimages0-a.akamaihd.net/?l=a1464835-1%3Aboxblur%2810%25%2C10%25%29%3Ba1464835-1%3Aprimary%280.65%29%3B%240%3Aoverlay%28%241%29%3Ba1464835-1%3Apad%2850%25%29%3B%242%3Aoverlay%28%243%29", 
     "price": null, 
     "trackNum": 6, 
     "albumArtistKey": "r778143", 
     "key": "t16421931", 
     "icon": "http://img02.cdn2-rdio.com/album/3/0/a/0000000000165a03/1/square-200.jpg", 
     "canSample": true, 
     "name": "Silver Rectangular Box", 
     "isExplicit": false, 
     "artist": "Cubik & Origami", 
     "url": "/artist/Cubik__Origami/album/Slept_In_On_Doomsday/track/Silver_Rectangular_Box/", 
     "icon400": "http://img00.cdn2-rdio.com/album/3/0/a/0000000000165a03/1/square-400.jpg", 
     "artistKey": "r778143", 
     "canDownload": false, 
     "length": 1, 
     "canTether": false, 
     "albumKey": "a1464835"
    }
   ], 
   "key": "p7202138", 
   "ownerUrl": "/people/walkaway/", 
   "embedUrl": "https://rd.io/e/QeHp7DMytxs/", 
   "owner": "Jeff Bonhag", 
   "type": "p", 
   "dynamicIcon": "http://rdiodynimages3-a.akamaihd.net/?l=a1464835-1%401/4%3B_%3Agrid%28%240%29"
  }
 }
}